braviapsk/__init__.py
braviapsk/sony_bravia_psk.py
braviapsk/version.py
pySonyBraviaPSK-0.2.4.dist-info/LICENSE
pySonyBraviaPSK-0.2.4.dist-info/METADATA
pySonyBraviaPSK-0.2.4.dist-info/WHEEL
pySonyBraviaPSK-0.2.4.dist-info/top_level.txt
pySonyBraviaPSK-0.2.4.dist-info/RECORD
