Metadata-Version: 2.1
Name: pySonyBraviaPSK
Version: 0.2.4
Summary: Library for Sony Bravia TVs with Pre-Shared Key option
Home-page: https://github.com/gerard33/sony_bravia_psk
Maintainer: Gerard
License: MIT
Keywords: Sony Bravia TV PSK for Home Assistant
Platform: UNKNOWN
License-File: LICENSE
Requires-Dist: requests
